dadastock/__init__.py
dadastock/apiException.py
dadastock/inventory.py
dadastock/stockAPI.py
dadastock/stockEnum.py
dadastock/tick.py
dadastock/trade.py
stockApi/__init__.py
stockApi/apiException.py
stockApi/dada_stock_api.py
stockApi/inventory.py
stockApi/stockAPI.py
stockApi/stockEnum.py
stockApi/tick.py
stockApi/trade.py
dadastockapi-2.4.3.dist-info/License.txt
dadastockapi-2.4.3.dist-info/METADATA
dadastockapi-2.4.3.dist-info/WHEEL
dadastockapi-2.4.3.dist-info/top_level.txt
dadastockapi-2.4.3.dist-info/RECORD
