Metadata-Version: 2.1
Name: dadastockapi
Version: 2.4.3
Summary: API for DaDaStock webiste
Home-page: https://github.com/charlie11438/DaDaStockAPI
Author: charlieDa
Author-email: charlieDa@tedu.tw
License: UNKNOWN
Platform: UNKNOWN
Classifier: Programming Language :: Python :: 3
Classifier: License :: OSI Approved :: MIT License
Classifier: Operating System :: OS Independent
Requires-Python: >=3.6
